LICENSE
LONG_DESCRIPTION.rst
MANIFEST.in
setup.py
gradientzoo/__init__.py
gradientzoo/client.py
gradientzoo/keras_client.py
gradientzoo/lasagne_client.py
gradientzoo/tensorflow_client.py
gradientzoo/version.py
gradientzoo.egg-info/PKG-INFO
gradientzoo.egg-info/SOURCES.txt
gradientzoo.egg-info/dependency_links.txt
gradientzoo.egg-info/requires.txt
gradientzoo.egg-info/top_level.txt